the_jira_cli/.example.env
the_jira_cli/__init__.py
the_jira_cli/jira.py
the_jira_cli/cli/__init__.py
the_jira_cli/commands/__init__.py
the_jira_cli/commands/audit_record/__init__.py
the_jira_cli/commands/board/__init__.py
the_jira_cli/commands/component/__init__.py
the_jira_cli/commands/dashboard/__init__.py
the_jira_cli/commands/filter/__init__.py
the_jira_cli/commands/group/__init__.py
the_jira_cli/commands/group/user/__init__.py
the_jira_cli/commands/issue/__init__.py
the_jira_cli/commands/issue/assignee/__init__.py
the_jira_cli/commands/issue/attachment/__init__.py
the_jira_cli/commands/issue/comment/__init__.py
the_jira_cli/commands/issue/field/__init__.py
the_jira_cli/commands/issue/label/__init__.py
the_jira_cli/commands/issue/permission/__init__.py
the_jira_cli/commands/issue/reporter/__init__.py
the_jira_cli/commands/issue/watcher/__init__.py
the_jira_cli/commands/issue/worklog/__init__.py
the_jira_cli/commands/project/__init__.py
the_jira_cli/commands/project/permission/__init__.py
the_jira_cli/commands/sprint/__init__.py
the_jira_cli/commands/tree/__init__.py
the_jira_cli/commands/user/__init__.py
the_jira_cli/commands/user/get.py
the_jira_cli/commands/user/avatar/__init__.py
the_jira_cli/commands/user/group/__init__.py
the_jira_cli/config/__init__.py
the_jira_cli-0.0.3.1.dist-info/METADATA
the_jira_cli-0.0.3.1.dist-info/WHEEL
the_jira_cli-0.0.3.1.dist-info/entry_points.txt
the_jira_cli-0.0.3.1.dist-info/top_level.txt
the_jira_cli-0.0.3.1.dist-info/RECORD
