Metadata-Version: 2.1
Name: the-jira-cli
Version: 0.0.3.1
Summary: Manage Jira from the Terminal
Author-email: Jonathan Llovet <jonathan.llovet@gmail.com>
License: MIT License
Project-URL: repository, https://github.com/jllovet/the-jira-cli
Project-URL: homepage, https://github.com/jllovet/the-jira-cli
Keywords: Jira,Atlassian,Project,Management,CLI
Classifier: Development Status :: 3 - Alpha
Classifier: Environment :: Console
Classifier: Intended Audience :: Developers
Classifier: Intended Audience :: Information Technology
Classifier: License :: OSI Approved :: MIT License
Classifier: Operating System :: OS Independent
Classifier: Programming Language :: Python
Requires-Python: >=3.7
Requires-Dist: click (~=7.1.2)
Requires-Dist: atlassian-python-api (~=3.28.0)
Requires-Dist: python-dotenv (~=0.21.0)
Requires-Dist: setuptools-scm (~=7.0.5)
